optipfair/__init__.py
optipfair/bias/__init__.py
optipfair/bias/activations.py
optipfair/bias/bias_visualization_example.py
optipfair/bias/defaults.py
optipfair/bias/metrics.py
optipfair/bias/utils.py
optipfair/bias/visualization.py
optipfair/cli/__init__.py
optipfair/cli/commands.py
optipfair/evaluation/__init__.py
optipfair/evaluation/benchmarks.py
optipfair/pruning/__init__.py
optipfair/pruning/depth.py
optipfair/pruning/mlp_glu.py
optipfair/pruning/utils.py
optipfair/pruning/future_extensions/__init__.py
optipfair/pruning/future_extensions/attention.py
optipfair/pruning/future_extensions/block.py
optipfair-0.2.3.dist-info/licenses/LICENSE
optipfair-0.2.3.dist-info/METADATA
optipfair-0.2.3.dist-info/WHEEL
optipfair-0.2.3.dist-info/entry_points.txt
optipfair-0.2.3.dist-info/top_level.txt
optipfair-0.2.3.dist-info/RECORD
