Metadata-Version: 2.4
Name: optipfair
Version: 0.2.3
Summary: A library for structured pruning & Bias visualization of large language models
Home-page: https://github.com/peremartra/optipfair
Author: Pere Martra
Author-email: peremartra@uadla.com
Classifier: Programming Language :: Python :: 3
Classifier: License :: OSI Approved :: Apache Software License
Classifier: Operating System :: OS Independent
Classifier: Development Status :: 3 - Alpha
Classifier: Intended Audience :: Science/Research
Classifier: Topic :: Scientific/Engineering :: Artificial Intelligence
Requires-Python: >=3.8
License-File: LICENSE
Requires-Dist: torch>=1.10.0
Requires-Dist: transformers>=4.25.0
Requires-Dist: tqdm>=4.62.0
Requires-Dist: click>=8.0.0
Provides-Extra: dev
Requires-Dist: pytest>=7.0.0; extra == "dev"
Requires-Dist: black>=22.0.0; extra == "dev"
Requires-Dist: flake8>=4.0.0; extra == "dev"
Requires-Dist: isort>=5.10.0; extra == "dev"
Requires-Dist: mypy>=0.900; extra == "dev"
Provides-Extra: eval
Requires-Dist: datasets>=2.0.0; extra == "eval"
Requires-Dist: numpy>=1.20.0; extra == "eval"
Requires-Dist: pandas>=1.3.0; extra == "eval"
Requires-Dist: matplotlib>=3.5.0; extra == "eval"
Requires-Dist: seaborn>=0.11.0; extra == "eval"
Provides-Extra: viz
Requires-Dist: matplotlib>=3.5.0; extra == "viz"
Requires-Dist: seaborn>=0.11.0; extra == "viz"
Requires-Dist: numpy>=1.20.0; extra == "viz"
Requires-Dist: pandas>=1.3.0; extra == "viz"
Requires-Dist: scikit-learn>=1.0.0; extra == "viz"
Dynamic: author
Dynamic: author-email
Dynamic: classifier
Dynamic: description
Dynamic: description-content-type
Dynamic: home-page
Dynamic: license-file
Dynamic: provides-extra
Dynamic: requires-dist
Dynamic: requires-python
Dynamic: summary
